jit/__init__.py
jit/cli.py
jit/constants.py
jit/llm.py
jit/prompts.py
jit/utils.py
jit_cli-0.1.2.dist-info/LICENSE
jit_cli-0.1.2.dist-info/METADATA
jit_cli-0.1.2.dist-info/WHEEL
jit_cli-0.1.2.dist-info/entry_points.txt
jit_cli-0.1.2.dist-info/top_level.txt
jit_cli-0.1.2.dist-info/RECORD
