Metadata-Version: 2.1
Name: jit-cli
Version: 0.1.2
Summary: A command line tool to automatically create pull requests on GitHub
Home-page: https://github.com/gsvh/jit
Author: George S. van Heerden
Author-email: georgesebastiaan.vh@gmail.com
License: MIT
Classifier: Development Status :: 3 - Alpha
Classifier: Environment :: Console
Classifier: Intended Audience :: Developers
Classifier: License :: OSI Approved :: MIT License
Classifier: Natural Language :: English
Classifier: Operating System :: MacOS
Classifier: Operating System :: POSIX :: Linux
Classifier: Programming Language :: Python :: 3.11
Classifier: Topic :: Software Development :: Version Control :: Git
Classifier: Topic :: Terminals
Classifier: Topic :: Text Processing :: Markup
Classifier: Topic :: Utilities
License-File: LICENSE
Requires-Dist: click ==8.1.7
Requires-Dist: GitPython ==3.1.43
Requires-Dist: rich ==13.7.1
Requires-Dist: ollama ==0.3.0
